skan/__init__.py
skan/basis.py
skan/skans.py
single_kan-0.2.0.dist-info/LICENSE
single_kan-0.2.0.dist-info/METADATA
single_kan-0.2.0.dist-info/WHEEL
single_kan-0.2.0.dist-info/top_level.txt
single_kan-0.2.0.dist-info/RECORD
