Metadata-Version: 2.1
Name: single-kan
Version: 0.2.0
Summary: Python libaray for SKAN (Single-parameterized KAN)
Home-page: https://github.com/chikkkit/SKAN
Author: Zhijie Chan
Author-email: zhijiechencs@gmail.com
Classifier: Programming Language :: Python :: 3
Classifier: License :: OSI Approved :: MIT License
Classifier: Operating System :: OS Independent
License-File: LICENSE
